{
  "step": 43,
  "eigenvalues": "[ 5.6476325e-02  4.6722107e-02  3.4175340e-02 ... -2.7675919e-09\n -2.9450860e-09 -3.2871794e-09]",
  "metrics": {
    "explained_variance_ratios": {
      "top_5": "0.5027403",
      "top_10": "0.70443845",
      "top_20": "0.9032627",
      "top_50": "0.9997905"
    },
    "effective_ranks": "21.023006",
    "spectral_norms": "0.056476325",
    "nuclear_norms": "0.36644474",
    "condition_numbers": "45798.73"
  },
  "timestamp": "2026-01-29T17:39:40.343908"
}